bottle_sitemap/__init__.py
bottle_sitemap/error.py
bottle_sitemap/plugin.py
bottle_sitemap-0.2.0.dist-info/LICENSE
bottle_sitemap-0.2.0.dist-info/METADATA
bottle_sitemap-0.2.0.dist-info/WHEEL
bottle_sitemap-0.2.0.dist-info/top_level.txt
bottle_sitemap-0.2.0.dist-info/RECORD
