Metadata-Version: 2.1
Name: bottle-sitemap
Version: 0.2.0
Summary: Plugin for generating a sitemap in Bottle web framework.
Home-page: https://github.com/m19t12/bottle-sitemap
Author: Manolis Tsoukalas
Author-email: emmtsoukalas@gmail.com
License: UNKNOWN
Platform: UNKNOWN
Classifier: Programming Language :: Python :: 3
Classifier: License :: OSI Approved :: GNU General Public License v3 (GPLv3)
Classifier: Operating System :: OS Independent
